<?xml version="1.0" encoding="utf-8"?>
<!DOCTYPE hibernate-mapping PUBLIC "-//Hibernate/Hibernate Mapping DTD 3.0//EN"
"http://www.hibernate.org/dtd/hibernate-mapping-3.0.dtd">
<!-- 
    Mapping file autogenerated by MyEclipse Persistence Tools
-->
<hibernate-mapping>
    <class name="com.entity.Staff" table="STAFF" schema="SCOTT">
        <id name="staffId" type="java.lang.String">
            <column name="STAFF_ID" length="12" />
            <generator class="assigned" />
        </id>
        <property name="staffName" type="java.lang.String">
            <column name="STAFF_NAME" length="12" not-null="true" />
        </property>
        <property name="staffSex" type="java.lang.Integer">
            <column name="STAFF_SEX" />
        </property>
        <property name="staffBirthday" type="java.util.Date">
            <column name="STAFF_BIRTHDAY" not-null="true" />
        </property>
        <property name="staffPhonenumber" type="java.lang.String">
            <column name="STAFF_PHONENUMBER" length="11" not-null="true" />
        </property>
        <property name="staffRole" type="java.lang.Integer">
            <column name="STAFF_ROLE" />
        </property>
        <set name="pickupBills" inverse="true">
            <key>
                <column name="STAFF_ID" length="12" />
            </key>
            <one-to-many class="com.entity.PickupBill" />
        </set>
        <set name="warehouses" inverse="true">
            <key>
                <column name="STAFF_ID" length="12" />
            </key>
            <one-to-many class="com.entity.Warehouse" />
        </set>
    </class>
</hibernate-mapping>
